src/__init__.py
src/__main__.py
src/convert.py
src/decorators/__init__.py
src/decorators/notNone.py
src/types/ColorComponents.py
src/types/Modes.py
src/types/__init__.py
src/utilities/__init__.py
src/utilities/binary.py
src/utilities/stegUtils.py
test/__init__.py
simple_steganography-1.0.1.dist-info/LICENSE
simple_steganography-1.0.1.dist-info/METADATA
simple_steganography-1.0.1.dist-info/WHEEL
simple_steganography-1.0.1.dist-info/entry_points.txt
simple_steganography-1.0.1.dist-info/top_level.txt
simple_steganography-1.0.1.dist-info/zip-safe
simple_steganography-1.0.1.dist-info/RECORD
