Metadata-Version: 2.1
Name: simple-steganography
Version: 1.0.1
Summary: Simple command line utility for steganography
Home-page: https://github.com/karafra/steg-utility/
Author: Karafra
Author-email: dariusKralovic@protonmail.com
License: Apache Software License
Project-URL: Bug Reports, https://github.com/karafra/steg-utility/issues
Project-URL: Changelog, https://github.com/karafra/steg-utility/blob/master/CHANGELOG.md
Project-URL: Source Code, https://github.com/karafra/steg-utility/
Keywords: steganography,cli,utility
Platform: any
Classifier: Development Status :: 3 - Alpha
Classifier: Intended Audience :: Developers
Classifier: License :: OSI Approved :: Apache Software License
Classifier: Operating System :: OS Independent
Classifier: Programming Language :: Python
Classifier: Programming Language :: Python :: 3.8
Classifier: Programming Language :: Python :: 3.9
Classifier: Topic :: Software Development :: Libraries :: Python Modules
Requires-Python: >=3.8.10
Requires-Dist: opencv-python
Requires-Dist: numpy
